project_builder/__init__.py
project_builder/project_builder.py
project_builder/project_structure.yaml
py_auto_structure-0.1.5.dist-info/METADATA
py_auto_structure-0.1.5.dist-info/WHEEL
py_auto_structure-0.1.5.dist-info/entry_points.txt
py_auto_structure-0.1.5.dist-info/top_level.txt
py_auto_structure-0.1.5.dist-info/RECORD
