Metadata-Version: 2.1
Name: py-auto-structure
Version: 0.1.5
Summary: A tool to create a directory structure based on a YAML file
Home-page: https://github.com/thauks/py-auto-structure
Author: Thauks
License: MIT
Keywords: directory,structure,YAML,tool
Classifier: Programming Language :: Python :: 3
Classifier: Operating System :: OS Independent
Requires-Python: >=3.6
Requires-Dist: pyyaml
Requires-Dist: wheel
Requires-Dist: setuptools
Requires-Dist: twine
